hogpylib/__init__.py
hogpylib/__main__.py
hogpylib/hog.py
hogpylib-1.0.2.data/data/data/car.jpg
hogpylib-1.0.2.data/data/data/people.jpg
hogpylib-1.0.2.data/data/examples/HOG_implementation.png
hogpylib-1.0.2.data/data/examples/HOG_people.png
hogpylib-1.0.2.data/data/examples/Hog_car.png
hogpylib-1.0.2.dist-info/LICENSE.txt
hogpylib-1.0.2.dist-info/METADATA
hogpylib-1.0.2.dist-info/WHEEL
hogpylib-1.0.2.dist-info/entry_points.txt
hogpylib-1.0.2.dist-info/top_level.txt
hogpylib-1.0.2.dist-info/RECORD
