Metadata-Version: 2.1
Name: hogpylib
Version: 1.0.2
Summary: Histogram of Gradients in Python from scratch
Home-page: https://github.com/shubhamwagh/HOG_python
Author: Shubham Wagh
Author-email: shubhamwagh48@gmail.com
License: MIT License        
Keywords: PyHOG,setuptools,development
Platform: Ubuntu 20.04
Platform: Windows
Classifier: Development Status :: 3 - Alpha
Classifier: Intended Audience :: Developers
Classifier: Topic :: Software Development :: Build Tools
Classifier: License :: OSI Approved :: MIT License
Classifier: Programming Language :: Python :: 3
Classifier: Programming Language :: Python :: 3.6
Classifier: Programming Language :: Python :: 3.7
Classifier: Programming Language :: Python :: 3.8
Classifier: Programming Language :: Python :: 3.9
Classifier: Programming Language :: Python :: 3.10
Classifier: Programming Language :: Python :: 3 :: Only
Requires-Python: >=3.6, <4
License-File: LICENSE.txt
Requires-Dist: scikit-image
